{
  "features": [
    { "attributes": { "2015年": 8.5 }, "geometry": { "x": 116.70, "y": 38.50 } },
    { "attributes": { "2015年": 15.2 }, "geometry": { "x": 117.00, "y": 38.25 } },
    { "attributes": { "2015年": 22.8 }, "geometry": { "x": 117.40, "y": 38.15 } },
    { "attributes": { "2015年": 35.0 }, "geometry": { "x": 117.80, "y": 38.20 } },
    { "attributes": { "2015年": 48.6 }, "geometry": { "x": 118.10, "y": 38.40 } },
    { "attributes": { "2015年": 12.0 }, "geometry": { "x": 116.60, "y": 38.80 } },
    { "attributes": { "2015年": 28.3 }, "geometry": { "x": 116.80, "y": 38.60 } },
    { "attributes": { "2015年": 42.5 }, "geometry": { "x": 117.10, "y": 38.50 } },
    { "attributes": { "2015年": 55.0 }, "geometry": { "x": 117.45, "y": 38.45 } },
    { "attributes": { "2015年": 70.2 }, "geometry": { "x": 117.80, "y": 38.55 } },
    { "attributes": { "2015年": 95.8 }, "geometry": { "x": 118.15, "y": 38.70 } },
    { "attributes": { "2015年": 18.5 }, "geometry": { "x": 116.55, "y": 39.10 } },
    { "attributes": { "2015年": 33.2 }, "geometry": { "x": 116.75, "y": 39.00 } },
    { "attributes": { "2015年": 45.2 }, "geometry": { "x": 117.00, "y": 38.80 } },
    { "attributes": { "2015年": 62.8 }, "geometry": { "x": 117.30, "y": 38.70 } },
    { "attributes": { "2015年": 85.6 }, "geometry": { "x": 117.60, "y": 38.75 } },
    { "attributes": { "2015年": 120.5 }, "geometry": { "x": 117.95, "y": 38.85 } },
    { "attributes": { "2015年": 145.0 }, "geometry": { "x": 118.25, "y": 39.00 } },
    { "attributes": { "2015年": 25.6 }, "geometry": { "x": 116.60, "y": 39.40 } },
    { "attributes": { "2015年": 38.5 }, "geometry": { "x": 116.85, "y": 39.25 } },
    { "attributes": { "2015年": 53.6 }, "geometry": { "x": 117.10, "y": 39.10 } },
    { "attributes": { "2015年": 72.1 }, "geometry": { "x": 117.40, "y": 39.05 } },
    { "attributes": { "2015年": 102.5 }, "geometry": { "x": 117.70, "y": 39.10 } },
    { "attributes": { "2015年": 135.8 }, "geometry": { "x": 118.00, "y": 39.20 } },
    { "attributes": { "2015年": 180.2 }, "geometry": { "x": 118.30, "y": 39.35 } },
    { "attributes": { "2015年": 30.1 }, "geometry": { "x": 116.72, "y": 39.55 } },
    { "attributes": { "2015年": 42.0 }, "geometry": { "x": 116.95, "y": 39.45 } },
    { "attributes": { "2015年": 58.4 }, "geometry": { "x": 117.20, "y": 39.35 } },
    { "attributes": { "2015年": 78.9 }, "geometry": { "x": 117.50, "y": 39.30 } },
    { "attributes": { "2015年": 110.8 }, "geometry": { "x": 117.80, "y": 39.40 } },
    { "attributes": { "2015年": 160.3 }, "geometry": { "x": 118.10, "y": 39.50 } },
    { "attributes": { "2015年": 36.9 }, "geometry": { "x": 116.80, "y": 39.75 } },
    { "attributes": { "2015年": 50.1 }, "geometry": { "x": 117.05, "y": 39.65 } },
    { "attributes": { "2015年": 67.2 }, "geometry": { "x": 117.35, "y": 39.55 } },
    { "attributes": { "2015年": 88.7 }, "geometry": { "x": 117.60, "y": 39.60 } },
    { "attributes": { "2015年": 115.0 }, "geometry": { "x": 117.90, "y": 39.70 } },
    { "attributes": { "2015年": 41.8 }, "geometry": { "x": 116.95, "y": 39.80 } },
    { "attributes": { "2015年": 64.3 }, "geometry": { "x": 117.25, "y": 39.75 } },
    { "attributes": { "2015年": 92.0 }, "geometry": { "x": 117.55, "y": 39.80 } },
    { "attributes": { "2015年": 130.6 }, "geometry": { "x": 117.80, "y": 39.90 } },
    { "attributes": { "2015年": 47.5 }, "geometry": { "x": 117.15, "y": 39.95 } },
    { "attributes": { "2015年": 74.0 }, "geometry": { "x": 117.45, "y": 39.95 } },
    { "attributes": { "2015年": 98.4 }, "geometry": { "x": 117.65, "y": 39.50 } },
    { "attributes": { "2015年": 76.3 }, "geometry": { "x": 117.35, "y": 39.18 } },
    { "attributes": { "2015年": 105.2 }, "geometry": { "x": 117.55, "y": 39.15 } },
    { "attributes": { "2015年": 21.0 }, "geometry": { "x": 116.90, "y": 38.40 } },
    { "attributes": { "2015年": 60.0 }, "geometry": { "x": 117.50, "y": 38.60 } },
    { "attributes": { "2015年": 82.1 }, "geometry": { "x": 117.70, "y": 38.40 } },
    { "attributes": { "2015年": 200.5 }, "geometry": { "x": 118.20, "y": 39.55 } },
    { "attributes": { "2015年": 155.0 }, "geometry": { "x": 118.05, "y": 39.00 } },
    { "attributes": { "2015年": 43.7 }, "geometry": { "x": 117.15, "y": 38.65 } },
    { "attributes": { "2015年": 56.8 }, "geometry": { "x": 117.25, "y": 38.40 } },
    { "attributes": { "2015年": 87.2 }, "geometry": { "x": 117.65, "y": 39.30 } },
    { "attributes": { "2015年": 140.0 }, "geometry": { "x": 118.10, "y": 38.95 } },
    { "attributes": { "2015年": 170.8 }, "geometry": { "x": 118.25, "y": 39.20 } },
    { "attributes": { "2015年": 230.0 }, "geometry": { "x": 118.30, "y": 39.50 } },
    { "attributes": { "2015年": 68.4 }, "geometry": { "x": 117.40, "y": 39.70 } },
    { "attributes": { "2015年": 48.9 }, "geometry": { "x": 117.20, "y": 39.50 } },
    { "attributes": { "2015年": 10.5 }, "geometry": { "x": 116.55, "y": 39.25 } },
    { "attributes": { "2015年": 190.0 }, "geometry": { "x": 118.15, "y": 39.30 } }
  ]
}
